apex_auth/__init__.py
apex_auth/apex_request.py
apex_auth-0.1.7.dist-info/METADATA
apex_auth-0.1.7.dist-info/RECORD
apex_auth-0.1.7.dist-info/WHEEL
apex_auth-0.1.7.dist-info/top_level.txt
