Metadata-Version: 2.1
Name: apex-auth
Version: 0.1.7
Summary: UNKNOWN
Home-page: https://github.com/promoteinternational/apex-ng-auth
Author: Andréas Kühne
Author-email: andreas.kuhne@promoteint.com
License: UNKNOWN
Platform: UNKNOWN
Classifier: Programming Language :: Python :: 3
Classifier: License :: OSI Approved :: MIT License
Classifier: Operating System :: OS Independent
Requires-Dist: Django (>=2.0.5djangorestframework>=3.8.2)
